{
    "os": "Linux-5.4.0-132-generic-x86_64-with-glibc2.31",
    "python": "3.10.4",
    "heartbeatAt": "2022-11-24T19:44:39.050768",
    "startedAt": "2022-11-24T19:44:37.576309",
    "docker": null,
    "cuda": null,
    "args": [
        "--amp"
    ],
    "state": "running",
    "program": "/home/hewei/TUM/Unet-pytorch/Pytorch-UNet/train.py",
    "codePath": "train.py",
    "git": {
        "remote": "https://github.com/milesial/Pytorch-UNet.git",
        "commit": "a013c80ca6b011ba34ba0700b961b77e0ed003a2"
    },
    "email": "ghw1515489084@gmail.com",
    "root": "/home/hewei/TUM/Unet-pytorch/Pytorch-UNet",
    "host": "hewei-Ubuntu",
    "username": "hewei",
    "executable": "/home/hewei/miniconda3/envs/i2dl/bin/python",
    "cpu_count": 4,
    "cpu_count_logical": 8,
    "cpu_freq": {
        "current": 3.1478749999999995,
        "min": 800.0,
        "max": 3500.0
    },
    "cpu_freq_per_core": [
        {
            "current": 3.125,
            "min": 800.0,
            "max": 3500.0
        },
        {
            "current": 3.146,
            "min": 800.0,
            "max": 3500.0
        },
        {
            "current": 3.173,
            "min": 800.0,
            "max": 3500.0
        },
        {
            "current": 3.147,
            "min": 800.0,
            "max": 3500.0
        },
        {
            "current": 3.1,
            "min": 800.0,
            "max": 3500.0
        },
        {
            "current": 3.15,
            "min": 800.0,
            "max": 3500.0
        },
        {
            "current": 3.171,
            "min": 800.0,
            "max": 3500.0
        },
        {
            "current": 3.171,
            "min": 800.0,
            "max": 3500.0
        }
    ],
    "disk": {
        "total": 130.35214233398438,
        "used": 71.0469741821289
    },
    "gpu": "NVIDIA GeForce GTX 950M",
    "gpu_count": 1,
    "gpu_devices": [
        {
            "name": "NVIDIA GeForce GTX 950M",
            "memory_total": 4294967296
        }
    ],
    "memory": {
        "total": 15.432609558105469
    }
}
